awsgen/__init__.py
awsgen/__main__.py
awsgen/app.py
awsgen/cli.py
awsgen/applications/__init__.py
awsgen/applications/account.py
awsgen/applications/configuration.py
awsgen/applications/profile.py
awsgen/applications/temporary.py
awsgen/command/__init__.py
awsgen/command/configure.py
awsgen/command/createprofile.py
awsgen/command/getactiveprofile.py
awsgen/command/getkey.py
awsgen/command/getlink.py
awsgen/command/listprofiles.py
awsgen/command/setactiveprofile.py
awsgen/models/__init__.py
awsgen/models/account.py
awsgen/models/configuration.py
awsgen/models/credentials.py
awsgen/models/profile.py
awsgen/models/request.py
awsgen-0.0.16.data/scripts/aws-gen
awsgen-0.0.16.data/scripts/aws-gen.cmd
awsgen-0.0.16.dist-info/LICENSE
awsgen-0.0.16.dist-info/METADATA
awsgen-0.0.16.dist-info/WHEEL
awsgen-0.0.16.dist-info/namespace_packages.txt
awsgen-0.0.16.dist-info/top_level.txt
awsgen-0.0.16.dist-info/RECORD
